relations_sql/__init__.py
relations_sql/clause.py
relations_sql/column.py
relations_sql/criteria.py
relations_sql/criterion.py
relations_sql/ddl.py
relations_sql/expression.py
relations_sql/index.py
relations_sql/query.py
relations_sql/sql.py
relations_sql/table.py
relations_sql-0.6.7.dist-info/LICENSE.txt
relations_sql-0.6.7.dist-info/METADATA
relations_sql-0.6.7.dist-info/WHEEL
relations_sql-0.6.7.dist-info/top_level.txt
relations_sql-0.6.7.dist-info/RECORD
