Metadata-Version: 2.1
Name: relations-sql
Version: 0.6.7
Home-page: https://github.com/relations-dil/python-relations-sql
Author: Gaffer Fitch
Author-email: relations@gaf3.com
Classifier: Programming Language :: Python :: 3
Classifier: License :: OSI Approved :: MIT License
License-File: LICENSE.txt
Requires-Dist: overscore (==0.1.1)
